{
  "id": "eumenes",
  "name": "Eumenes",
  "shortName": "Eumenes",
  "theory": "Self-play champion",
  "summary": "Self-play champion focused on church leverage and frontier defense, with holdout behavior showing low frontier defense, high land buying, high church giving, moderate revocation.",
  "source": "emergent-trained",
  "basePersonalityId": null,
  "weights": {
    "wealth": 0.71,
    "land": 2.172,
    "frontier": 2.256,
    "capital": 1.051,
    "throne": 1.452,
    "church": 2.319,
    "loyalty": 1.854,
    "retaliation": 1.83,
    "selfAppointment": 2.194,
    "mercenary": 0.901,
    "revocation": 0.785
  },
  "tactics": {
    "independence": 1.52,
    "frontierAlarm": 0.768,
    "churchReserve": 1.024,
    "incumbencyGrip": 1.035
  },
  "meta": {
    "affinitySlope": 0.4352,
    "bandwagonStrength": 1.5741,
    "independenceDamping": 0.7827,
    "selfThroneBoost": 4,
    "incumbentGrip": 1.2496,
    "coupGrievanceFactor": 0.7234,
    "incomeHorizonBase": 1.2452,
    "incomeHorizonGrowth": 0.2763,
    "mercenaryThreshold": 0.1613,
    "frontierAlarmDanger": 0.8226,
    "recruitThreshold": 0,
    "landPurchaseThreshold": 0.61,
    "churchGiftThreshold": 0,
    "dismissalThreshold": 1.8945,
    "revocationThreshold": 5.9858,
    "courtTemperature": 1.8721,
    "orderTemperature": 0.727,
    "supportTemperature": 0.2951,
    "opponentLearnRate": 0.3279,
    "opponentTrust": 0.3701
  },
  "training": {
    "generation": 100,
    "matches": 128,
    "wins": 6,
    "winShare": 0.0469,
    "championScore": 5.597,
    "averageFitness": -7.313,
    "averageScore": 1.95,
    "averageWealth": 1.95,
    "empireFallRate": 0.7734,
    "fitnessVariance": 86.8258,
    "fitnessPresetId": "custom",
    "playerCount": 5,
    "deckSize": 9,
    "populationPresetId": "emergent-self-play",
    "seed": "20260429",
    "trainedAt": "2026-05-12T18:17:14.729Z",
    "trainMatches": 10,
    "validationMatches": 8,
    "holdoutMatches": 128,
    "trainWinShare": 0.1,
    "validationWinShare": 0.0417,
    "holdoutWinShare": 0.0469,
    "trainEmpireFallRate": 0.3,
    "validationEmpireFallRate": 0.75,
    "holdoutEmpireFallRate": 0.7734,
    "trainScorePercentile": 0.7,
    "validationScorePercentile": 0.75,
    "holdoutScorePercentile": 0.6445,
    "trainWealthPercentile": 0.7,
    "validationWealthPercentile": 0.75,
    "holdoutWealthPercentile": 0.6445,
    "guardRate": 0,
    "paretoFront": 1,
    "crowdingDistance": 0,
    "noveltyScore": 0.2402,
    "noveltyPercentile": 0.3,
    "seatBias": -0.0594,
    "bestMatchup": "hof:generation_bucket_6",
    "worstMatchup": "hof:generation_bucket_3",
    "mainBehavior": "low frontier defense, high land buying, high church giving, moderate revocation",
    "behaviorProfile": {
      "frontierTroopShare": 0.1278,
      "capitalTroopShare": 0.8722,
      "averageLandBuys": 7.5313,
      "averageChurchGifts": 1.3516,
      "averageRevocations": 0.4766,
      "averageDefenderRewards": 0.4844,
      "averageThroneCaptures": 0.6875,
      "incumbentSupportRate": 0.3176,
      "selfSupportRate": 0.7205,
      "goldHoardingRate": 0.2281,
      "averageMercSpend": 9.0469,
      "recruitmentUtilization": 0.6612
    },
    "perOpponentTypeWinRate": {
      "scripted:always_coup_leader": {
        "matches": 16,
        "winRate": 0.0781,
        "averageFitness": -5.9592
      },
      "hof:generation_bucket_9": {
        "matches": 4,
        "winRate": 0,
        "averageFitness": -12
      },
      "emergent:cluster_3": {
        "matches": 4.5,
        "winRate": 0.0278,
        "averageFitness": -8.7407
      },
      "scripted:always_buy_land": {
        "matches": 16,
        "winRate": 0.0391,
        "averageFitness": -8.5352
      },
      "hof:generation_bucket_4": {
        "matches": 8,
        "winRate": 0.1094,
        "averageFitness": -4.3733
      },
      "scripted:always_gift_to_church": {
        "matches": 16,
        "winRate": 0.0156,
        "averageFitness": -8.6667
      },
      "emergent:cluster_2": {
        "matches": 8.5,
        "winRate": 0.0882,
        "averageFitness": -5.2925
      },
      "hof:generation_bucket_8": {
        "matches": 6,
        "winRate": 0.0417,
        "averageFitness": -7.4977
      },
      "hof:generation_bucket_3": {
        "matches": 6,
        "winRate": 0,
        "averageFitness": -8.3218
      },
      "hof:generation_bucket_5": {
        "matches": 4,
        "winRate": 0.0313,
        "averageFitness": -5.1892
      },
      "emergent:cluster_0": {
        "matches": 14.5,
        "winRate": 0.0431,
        "averageFitness": -7.5077
      },
      "scripted:always_support_richest_rival": {
        "matches": 16,
        "winRate": 0.0547,
        "averageFitness": -6.0907
      },
      "hof:generation_bucket_6": {
        "matches": 2,
        "winRate": 0.125,
        "averageFitness": -5.6771
      },
      "emergent:cluster_1": {
        "matches": 4.5,
        "winRate": 0,
        "averageFitness": -9.0741
      },
      "hof:generation_bucket_2": {
        "matches": 2,
        "winRate": 0,
        "averageFitness": -12
      }
    },
    "perSeatWinRate": {
      "0": {
        "matches": 26,
        "winRate": 0.0577,
        "averageFitness": -7.5406
      },
      "1": {
        "matches": 26,
        "winRate": 0.0192,
        "averageFitness": -7.0972
      },
      "2": {
        "matches": 26,
        "winRate": 0.0577,
        "averageFitness": -5.9295
      },
      "3": {
        "matches": 25,
        "winRate": 0.06,
        "averageFitness": -6.7811
      },
      "4": {
        "matches": 25,
        "winRate": 0.04,
        "averageFitness": -9.2711
      }
    }
  }
}
