{
  "id": "ezekias",
  "name": "Ezekias",
  "shortName": "Ezekias",
  "theory": "Self-play champion",
  "summary": "Self-play champion focused on throne pressure and self-promotion, with holdout behavior showing low frontier defense, high land buying, high revocation.",
  "source": "emergent-trained",
  "basePersonalityId": null,
  "weights": {
    "wealth": 2.39,
    "land": 1.789,
    "frontier": 1.161,
    "capital": 1.568,
    "throne": 3.049,
    "church": 2.686,
    "loyalty": 0.927,
    "retaliation": 2.713,
    "selfAppointment": 2.886,
    "mercenary": 1.205,
    "revocation": 2.702
  },
  "tactics": {
    "independence": 0.72,
    "frontierAlarm": 1.224,
    "churchReserve": 0.7,
    "incumbencyGrip": 1.146
  },
  "meta": {
    "affinitySlope": 0.4083,
    "bandwagonStrength": 1.3325,
    "independenceDamping": 0.5068,
    "selfThroneBoost": 1.8362,
    "incumbentGrip": 2.4731,
    "coupGrievanceFactor": 1.1336,
    "incomeHorizonBase": 1.3721,
    "incomeHorizonGrowth": 0.7336,
    "mercenaryThreshold": 0.6131,
    "frontierAlarmDanger": 0.9726,
    "recruitThreshold": 1.7467,
    "landPurchaseThreshold": 0.8575,
    "churchGiftThreshold": 2.2268,
    "dismissalThreshold": 1.6655,
    "revocationThreshold": 1.2804,
    "courtTemperature": 0.507,
    "orderTemperature": 0.9522,
    "supportTemperature": 0.42,
    "opponentLearnRate": 0.3093,
    "opponentTrust": 0.2962
  },
  "training": {
    "generation": 60,
    "matches": 128,
    "wins": 16.5,
    "winShare": 0.1289,
    "championScore": 8.954,
    "averageFitness": -0.677,
    "averageWealth": 15.15,
    "empireFallRate": 0.4375,
    "fitnessVariance": 143.3396,
    "fitnessPresetId": "custom",
    "playerCount": 5,
    "deckSize": 9,
    "populationPresetId": "emergent-self-play",
    "seed": "20260429",
    "trainedAt": "2026-05-02T00:51:49.433Z",
    "trainMatches": 64,
    "validationMatches": 8,
    "holdoutMatches": 128,
    "trainWinShare": 0.1563,
    "validationWinShare": 0.125,
    "holdoutWinShare": 0.1289,
    "trainEmpireFallRate": 0.2969,
    "validationEmpireFallRate": 0.5,
    "holdoutEmpireFallRate": 0.4375,
    "trainWealthPercentile": 0.4531,
    "validationWealthPercentile": 0.5313,
    "holdoutWealthPercentile": 0.4746,
    "guardRate": 0,
    "paretoFront": 1,
    "crowdingDistance": 0,
    "noveltyScore": 0.3316,
    "noveltyPercentile": 0.7667,
    "seatBias": -0.046,
    "bestMatchup": "legacy:zealot",
    "worstMatchup": "legacy:hawk",
    "mainBehavior": "low frontier defense, high land buying, high revocation",
    "behaviorProfile": {
      "frontierTroopShare": 0,
      "capitalTroopShare": 1,
      "averageLandBuys": 6.5156,
      "averageChurchGifts": 0.8203,
      "averageRevocations": 6.7109,
      "averageThroneCaptures": 0.4297,
      "incumbentSupportRate": 0.4733,
      "selfSupportRate": 0.353,
      "goldHoardingRate": 0,
      "averageMercSpend": 20.2266,
      "recruitmentUtilization": 0.9599
    },
    "perOpponentTypeWinRate": {
      "scripted:always_coup_leader": {
        "matches": 6.25,
        "winRate": 0.04,
        "averageFitness": -6.8588
      },
      "legacy:opportunist": {
        "matches": 4.5,
        "winRate": 0.1667,
        "averageFitness": -0.6339
      },
      "hof:generation_bucket_1": {
        "matches": 7.75,
        "winRate": 0.1935,
        "averageFitness": 1.086
      },
      "emergent:cluster_2": {
        "matches": 8,
        "winRate": 0.1406,
        "averageFitness": -1.6812
      },
      "hof:generation_bucket_0": {
        "matches": 7.25,
        "winRate": 0.069,
        "averageFitness": -2.7737
      },
      "scripted:always_gift_to_church": {
        "matches": 7,
        "winRate": 0.0714,
        "averageFitness": -4.6918
      },
      "emergent:cluster_0": {
        "matches": 10.75,
        "winRate": 0.1395,
        "averageFitness": 0.7879
      },
      "scripted:always_punish_revocations": {
        "matches": 7,
        "winRate": 0.0714,
        "averageFitness": -2.4661
      },
      "legacy:steward": {
        "matches": 5,
        "winRate": 0.1,
        "averageFitness": -0.6772
      },
      "hof:generation_bucket_4": {
        "matches": 2,
        "winRate": 0.125,
        "averageFitness": -2.7095
      },
      "hof:generation_bucket_2": {
        "matches": 3.5,
        "winRate": 0.2143,
        "averageFitness": 4.9971
      },
      "emergent:cluster_1": {
        "matches": 3.5,
        "winRate": 0.1429,
        "averageFitness": -4.0713
      },
      "scripted:free_rider": {
        "matches": 6.5,
        "winRate": 0.0962,
        "averageFitness": -0.2681
      },
      "scripted:frontier_defender": {
        "matches": 6.25,
        "winRate": 0.18,
        "averageFitness": 4.6615
      },
      "legacy:magnate": {
        "matches": 4,
        "winRate": 0.25,
        "averageFitness": 0.5348
      },
      "hof:generation_bucket_5": {
        "matches": 4.75,
        "winRate": 0.0526,
        "averageFitness": 0.2346
      },
      "scripted:always_support_incumbent": {
        "matches": 6,
        "winRate": 0.2083,
        "averageFitness": 5.4146
      },
      "scripted:always_support_richest_rival": {
        "matches": 6,
        "winRate": 0.0833,
        "averageFitness": -1.6855
      },
      "legacy:hawk": {
        "matches": 4,
        "winRate": 0,
        "averageFitness": -6.1537
      },
      "scripted:always_buy_land": {
        "matches": 6,
        "winRate": 0.125,
        "averageFitness": -2.4211
      },
      "emergent:cluster_3": {
        "matches": 3.5,
        "winRate": 0.1429,
        "averageFitness": 1.097
      },
      "legacy:zealot": {
        "matches": 4,
        "winRate": 0.2813,
        "averageFitness": 3.4728
      },
      "legacy:reciprocator": {
        "matches": 4,
        "winRate": 0.1875,
        "averageFitness": 0.5278
      },
      "hof:generation_bucket_3": {
        "matches": 0.5,
        "winRate": 0,
        "averageFitness": -4.5652
      }
    },
    "perSeatWinRate": {
      "0": {
        "matches": 26,
        "winRate": 0.3077,
        "averageFitness": 4.5474
      },
      "1": {
        "matches": 26,
        "winRate": 0.1154,
        "averageFitness": -2.3289
      },
      "2": {
        "matches": 26,
        "winRate": 0,
        "averageFitness": -1.3761
      },
      "3": {
        "matches": 25,
        "winRate": 0.14,
        "averageFitness": -3.3385
      },
      "4": {
        "matches": 25,
        "winRate": 0.08,
        "averageFitness": -1.0026
      }
    }
  }
}
